tests/__init__.py
tests/test_voices.py
voices/__init__.py
voices/errors.py
voices/logger.py
voices/utils.py
voices/validations.py
voices/voices.py
voices_client-0.2.5.dist-info/LICENCE
voices_client-0.2.5.dist-info/METADATA
voices_client-0.2.5.dist-info/WHEEL
voices_client-0.2.5.dist-info/top_level.txt
voices_client-0.2.5.dist-info/RECORD
