Metadata-Version: 2.1
Name: voices-client
Version: 0.2.5
Summary: Voices client
Home-page: https://github.com/Fondeadora/voices-client.git
Author: Fondeadora
Author-email: tech@fondeadora.com
License: UNKNOWN
Keywords: client,voices,package
Platform: UNKNOWN
Classifier: Programming Language :: Python :: 3.6
Classifier: Programming Language :: Python :: 3.7
Classifier: Programming Language :: Python :: 3.8
Classifier: License :: OSI Approved :: MIT License
Classifier: Operating System :: OS Independent
Requires-Python: >=3.6
